{"county":"Broomfield","behavioralhealthorganizationbhonameentity":"Foothills Behavioral Health Partners","bhophone1":"303-432-5950","bhophone2":"866-245-1959 (Toll Free)","bhowebsite":"http://fbhpartners.com/","regionalcarecollaborativeorganizationrccoregion":"6","rcconameentity":"Colorado Community Health Alliance","rccophone1":"303-256-1717","rccophone2":"855-627-4685 (Toll Free)","rccowebsite":"http://www.cchacares.com/","judicialdistrictnumber":"17","probationcontactfname":"Michael","probationcontactlname":"Garcia","probationcontacttitle":"Chief Probation Officer","probationphone1":"303-255-4226","probationemail":"michael.garcia@judicial.state.co.us","probationwebsite":"http://www.courts.state.co.us/Probation/County/Index.cfm?County_ID=56","parole1contactfname":"Kelly","parole1contactlname":"Messamore","parole1contacttitle":"Assistant Director Operations","parole1phone1":"719-351-3738","parole1email":"kelly.messamore@state.co.us","parole1website":"https://www.colorado.gov/pacific/cdoc/adult-parole","jailnameentity":"Broomfield County Detention Center","jailphone1":"720-887-2000","jailwebsite":"http://www.broomfield.org/index.aspx?nid=299"}